gurtlib/__init__.py
gurtlib-1.0.3.dist-info/METADATA
gurtlib-1.0.3.dist-info/WHEEL
gurtlib-1.0.3.dist-info/RECORD
