Metadata-Version: 2.4
Name: gurtlib
Version: 1.0.3
Summary: A community-maintained framework that makes creating Gurt websites easy.
Author-email: Jasper Green <jasper@jasperdev.org>
License-Expression: CC-BY-NC-SA-4.0
Classifier: Operating System :: OS Independent
Classifier: Programming Language :: Python :: 3
Requires-Python: >=3.9
